odoo/addons/hr_timesheet_sheet_autodraft/README.rst
odoo/addons/hr_timesheet_sheet_autodraft/__init__.py
odoo/addons/hr_timesheet_sheet_autodraft/__manifest__.py
odoo/addons/hr_timesheet_sheet_autodraft/i18n/hr_timesheet_sheet_autodraft.pot
odoo/addons/hr_timesheet_sheet_autodraft/i18n/it.po
odoo/addons/hr_timesheet_sheet_autodraft/i18n/nl.po
odoo/addons/hr_timesheet_sheet_autodraft/models/__init__.py
odoo/addons/hr_timesheet_sheet_autodraft/models/account_analytic_line.py
odoo/addons/hr_timesheet_sheet_autodraft/models/res_company.py
odoo/addons/hr_timesheet_sheet_autodraft/models/res_config.py
odoo/addons/hr_timesheet_sheet_autodraft/readme/CONFIGURE.md
odoo/addons/hr_timesheet_sheet_autodraft/readme/CONTRIBUTORS.md
odoo/addons/hr_timesheet_sheet_autodraft/readme/DESCRIPTION.md
odoo/addons/hr_timesheet_sheet_autodraft/static/description/icon.png
odoo/addons/hr_timesheet_sheet_autodraft/static/description/index.html
odoo/addons/hr_timesheet_sheet_autodraft/tests/__init__.py
odoo/addons/hr_timesheet_sheet_autodraft/tests/test_hr_timesheet_sheet_autodraft.py
odoo/addons/hr_timesheet_sheet_autodraft/views/account_analytic_line.xml
odoo/addons/hr_timesheet_sheet_autodraft/views/res_config_settings.xml
odoo_addon_hr_timesheet_sheet_autodraft-18.0.1.0.0.2.dist-info/METADATA
odoo_addon_hr_timesheet_sheet_autodraft-18.0.1.0.0.2.dist-info/WHEEL
odoo_addon_hr_timesheet_sheet_autodraft-18.0.1.0.0.2.dist-info/top_level.txt
odoo_addon_hr_timesheet_sheet_autodraft-18.0.1.0.0.2.dist-info/RECORD
