Metadata-Version: 2.1
Name: odoo-addon-hr_timesheet_sheet_autodraft
Version: 18.0.1.0.0.2
Requires-Python: >=3.10
Requires-Dist: odoo-addon-hr_timesheet_sheet==18.0.*
Requires-Dist: odoo==18.0.*
Summary: Automatically draft a Timesheet Sheet for every time entry that does not have a relevant Timesheet Sheet existing.
Home-page: https://github.com/OCA/timesheet
License: AGPL-3
Author: CorporateHub, Odoo Community Association (OCA)
Author-email: support@odoo-community.org
Classifier: Programming Language :: Python
Classifier: Framework :: Odoo
Classifier: Framework :: Odoo :: 18.0
Classifier: License :: OSI Approved :: GNU Affero General Public License v3
